opsgeniecli/_version.py
opsgeniecli/cli.py
opsgeniecli/helper.py
opsgeniecli/commands/__init__.py
opsgeniecli/commands/alert_policies.py
opsgeniecli/commands/alerts.py
opsgeniecli/commands/commands.py
opsgeniecli/commands/config.py
opsgeniecli/commands/escalations.py
opsgeniecli/commands/heartbeat.py
opsgeniecli/commands/integrations.py
opsgeniecli/commands/logs.py
opsgeniecli/commands/maintenance_policies.py
opsgeniecli/commands/notification_policies.py
opsgeniecli/commands/on_call.py
opsgeniecli/commands/schedules.py
opsgeniecli/commands/teams.py
opsgeniecli/commands/teams_routing_rules.py
opsgeniecli/commands/users.py
opsgeniecli-0.5.5.dist-info/METADATA
opsgeniecli-0.5.5.dist-info/WHEEL
opsgeniecli-0.5.5.dist-info/entry_points.txt
opsgeniecli-0.5.5.dist-info/top_level.txt
opsgeniecli-0.5.5.dist-info/RECORD
