Metadata-Version: 2.4
Name: opsgeniecli
Version: 0.5.5
Summary: Add your description here
Requires-Python: >=3.10
Requires-Dist: opsgenielib
Requires-Dist: typer>=0.15.1
